cli.py
semantic_firewall.py
aegis_semantic_firewall-0.1.1.dist-info/licenses/LICENSE
api/__init__.py
api/app.py
detectors/__init__.py
detectors/echo_chamber.py
detectors/heuristic_detector.py
detectors/injection_detector.py
detectors/rule_based.py
aegis_semantic_firewall-0.1.1.dist-info/METADATA
aegis_semantic_firewall-0.1.1.dist-info/WHEEL
aegis_semantic_firewall-0.1.1.dist-info/entry_points.txt
aegis_semantic_firewall-0.1.1.dist-info/top_level.txt
aegis_semantic_firewall-0.1.1.dist-info/RECORD
